logcore/__init__.py
logcore/config.py
logcore/formatters.py
logcore/handlers.py
logcore/logger.py
logcore/utils.py
logcore-0.1.4.dist-info/licenses/LICENSE
logcore-0.1.4.dist-info/METADATA
logcore-0.1.4.dist-info/WHEEL
logcore-0.1.4.dist-info/top_level.txt
logcore-0.1.4.dist-info/RECORD
