Metadata-Version: 2.4
Name: logcore
Version: 0.1.4
Summary: A production-ready structured logging library for Python
Author-email: LogCore Contributors <rana.sarkar@ragnosticai.com>
Maintainer-email: LogCore Contributors <support@ragnosticai.com>
License: MIT License
Project-URL: Homepage, https://github.com/SarkarRana/logcore
Project-URL: Bug Reports, https://github.com/SarkarRana/logcore/issues
Project-URL: Source, https://github.com/SarkarRana/logcore
Project-URL: Documentation, https://github.com/SarkarRana/logcore#readme
Keywords: logging,structured-logging,json,observability,microservices
Classifier: Development Status :: 4 - Beta
Classifier: Intended Audience :: Developers
Classifier: License :: OSI Approved :: MIT License
Classifier: Operating System :: OS Independent
Classifier: Programming Language :: Python :: 3
Classifier: Programming Language :: Python :: 3.8
Classifier: Programming Language :: Python :: 3.9
Classifier: Programming Language :: Python :: 3.10
Classifier: Programming Language :: Python :: 3.11
Classifier: Programming Language :: Python :: 3.12
Classifier: Topic :: Software Development :: Libraries :: Python Modules
Classifier: Topic :: System :: Logging
Requires-Python: >=3.8
License-File: LICENSE
Provides-Extra: colors
Requires-Dist: colorama>=0.4.0; extra == "colors"
Provides-Extra: dev
Requires-Dist: pytest>=7.0.0; extra == "dev"
Requires-Dist: pytest-cov>=4.0.0; extra == "dev"
Requires-Dist: pytest-asyncio>=0.21.0; extra == "dev"
Requires-Dist: black>=23.0.0; extra == "dev"
Requires-Dist: isort>=5.12.0; extra == "dev"
Requires-Dist: flake8>=6.0.0; extra == "dev"
Requires-Dist: mypy>=1.0.0; extra == "dev"
Requires-Dist: pre-commit>=3.0.0; extra == "dev"
Provides-Extra: docs
Requires-Dist: sphinx>=6.0.0; extra == "docs"
Requires-Dist: sphinx-rtd-theme>=1.2.0; extra == "docs"
Requires-Dist: sphinx-autodoc-typehints>=1.19.0; extra == "docs"
Dynamic: license-file
